fluent/__init__.py
fluent/migrate/__init__.py
fluent/migrate/_context.py
fluent/migrate/blame.py
fluent/migrate/changesets.py
fluent/migrate/context.py
fluent/migrate/errors.py
fluent/migrate/evaluator.py
fluent/migrate/helpers.py
fluent/migrate/merge.py
fluent/migrate/repo_client.py
fluent/migrate/tool.py
fluent/migrate/transforms.py
fluent/migrate/util.py
fluent/migrate/validator.py
fluent.migrate-0.13.1.dist-info/LICENSE
fluent.migrate-0.13.1.dist-info/METADATA
fluent.migrate-0.13.1.dist-info/WHEEL
fluent.migrate-0.13.1.dist-info/entry_points.txt
fluent.migrate-0.13.1.dist-info/top_level.txt
fluent.migrate-0.13.1.dist-info/RECORD
