Metadata-Version: 2.1
Name: fluent.migrate
Version: 0.13.1
Summary: Toolchain to migrate legacy translation to Fluent.
Home-page: https://github.com/mozilla/fluent-migrate
Author: Mozilla
Author-email: l10n-drivers@mozilla.org
License: APL 2
Keywords: fluent,localization,l10n
Classifier: Development Status :: 3 - Alpha
Classifier: Intended Audience :: Developers
Classifier: License :: OSI Approved :: Apache Software License
Classifier: Operating System :: POSIX
Classifier: Programming Language :: Python :: 3.8
Classifier: Programming Language :: Python :: 3.9
Classifier: Programming Language :: Python :: 3.10
Classifier: Programming Language :: Python :: 3.11
Classifier: Programming Language :: Python :: 3.12
License-File: LICENSE
Requires-Dist: compare-locales <10.0,>=9.0.1
Requires-Dist: fluent.syntax <0.20,>=0.19.0
Provides-Extra: hg
Requires-Dist: python-hglib ; extra == 'hg'
